[
  {
    "id": 1,
    "name": "Koenigsegg",
    "type": "Sport",
    "pricePerDay": 99.00,
    "fuel": "90L",
    "transmission": "Manual",
    "capacity": "2 People",
    "rating": 4.8,
    "reviewCount": 350,
    "description": "The ultimate sports car for thrill seekers, combining speed and luxury.",
    "image": "Koenigsegg.png"
  },
  {
    "id": 2,
    "name": "Nissan GT - R",
    "type": "Sport",
    "pricePerDay": 82.00,
    "fuel": "80L",
    "transmission": "Manual",
    "capacity": "2 People",
    "rating": 4.7,
    "reviewCount": 440,
    "description": "NISMO embodies outstanding performance inspired by the race track.",
    "image": "Nissan-GT-R.png"
  },
  {
    "id": 3,
    "name": "Rolls-Royce",
    "type": "Sport",
    "pricePerDay": 96.00,
    "fuel": "70L",
    "transmission": "Manual",
    "capacity": "4 People",
    "rating": 4.9,
    "reviewCount": 220,
    "description": "Experience the pinnacle of luxury and performance in a single car.",
    "image": "Rolls-Royce.png"
  },
  {
    "id": 4,
    "name": "All New Rush",
    "type": "SUV",
    "pricePerDay": 76.00,
    "fuel": "70L",
    "transmission": "Manual",
    "capacity": "6 People",
    "rating": 4.5,
    "reviewCount": 310,
    "description": "A reliable and spacious SUV designed for family adventures.",
    "image": "All-New-Rush.png"
  },
  {
    "id": 5,
    "name": "CR - V",
    "type": "SUV",
    "pricePerDay": 80.00,
    "fuel": "80L",
    "transmission": "Manual",
    "capacity": "6 People",
    "rating": 4.6,
    "reviewCount": 290,
    "description": "The perfect blend of style and utility for every journey.",
    "image": "CR-V.png"
  },
  {
    "id": 6,
    "name": "All New Terios",
    "type": "SUV",
    "pricePerDay": 74.00,
    "fuel": "90L",
    "transmission": "Manual",
    "capacity": "6 People",
    "rating": 4.4,
    "reviewCount": 200,
    "description": "An SUV with great fuel efficiency and room for everyone.",
    "image": "All-New-Terios.png"
  },
  {
    "id": 7,
    "name": "MG ZX Exclusice",
    "type": "Hatchback",
    "pricePerDay": 76.00,
    "fuel": "70L",
    "transmission": "Electric",
    "capacity": "4 People",
    "rating": 4.3,
    "reviewCount": 150,
    "description": "A compact electric car perfect for city driving.",
    "image": "MG-ZX-Exclusice.png"
  },
  {
    "id": 8,
    "name": "New MG ZS",
    "type": "SUV",
    "pricePerDay": 80.00,
    "fuel": "80L",
    "transmission": "Manual",
    "capacity": "6 People",
    "rating": 4.5,
    "reviewCount": 220,
    "description": "A modern SUV with advanced features for every adventure.",
    "image": "New-MG-ZS.png"
  },
  {
    "id": 9,
    "name": "MG ZX Excite",
    "type": "Hatchback",
    "pricePerDay": 74.00,
    "fuel": "90L",
    "transmission": "Electric",
    "capacity": "4 People",
    "rating": 4.2,
    "reviewCount": 180,
    "description": "An efficient and eco-friendly hatchback for urban lifestyles.",
    "image": "MG-ZX-Excite.png"
  },
  {
    "id": 10,
    "name": "Mercedes Benz",
    "type": "Sedan",
    "pricePerDay": 76.00,
    "fuel": "70L",
    "transmission": "Electric",
    "capacity": "4 People",
    "rating": 4.8,
    "reviewCount": 300,
    "description": "A luxurious sedan that redefines elegance and comfort.",
    "image": "Rolls-Royce.png"
  },
  {
    "id": 11,
    "name": "Mini Cooper",
    "type": "Coupe",
    "pricePerDay": 80.00,
    "fuel": "80L",
    "transmission": "Manual",
    "capacity": "4 People",
    "rating": 4.7,
    "reviewCount": 250,
    "description": "A stylish coupe with exceptional performance for city drives.",
    "image": "Nissan-GT-R.png"
  },
  {
    "id": 12,
    "name": "Pegout 208",
    "type": "MPV",
    "pricePerDay": 74.00,
    "fuel": "90L",
    "transmission": "Electric",
    "capacity": "4 People",
    "rating": 4.3,
    "reviewCount": 200,
    "description": "An eco-friendly MPV with great comfort for long journeys.",
    "image": "Koenigsegg.png"
  }
]
